kipart/__init__.py
kipart/compare_symbols.py
kipart/kipart.py
kipart/random_symbol.py
kipart/version.py
kipart-2.3.0.dist-info/licenses/AUTHORS.md
kipart-2.3.0.dist-info/licenses/LICENSE
kipart-2.3.0.dist-info/METADATA
kipart-2.3.0.dist-info/WHEEL
kipart-2.3.0.dist-info/entry_points.txt
kipart-2.3.0.dist-info/top_level.txt
kipart-2.3.0.dist-info/RECORD
