Metadata-Version: 2.4
Name: kipart
Version: 2.3.0
Summary: Utilities for converting rows of CSV pin data into KiCad symbols and back.
Author-email: Dave Vandenbout <dave@vdb.name>
License: MIT
Project-URL: Homepage, https://github.com/devbisme/kipart
Project-URL: Source Code, https://github.com/devbisme/kipart
Project-URL: Documentation, https://github.com/devbisme/kipart#readme
Project-URL: Bug Tracker, https://github.com/devbisme/kipart/issues
Project-URL: Changelog, https://github.com/devbisme/kipart/blob/master/HISTORY.md
Keywords: kipart,KiCad,electronic,circuit,schematics,EDA,CSV,symbol
Classifier: Development Status :: 3 - Alpha
Classifier: Intended Audience :: Developers
Classifier: Intended Audience :: Science/Research
Classifier: License :: OSI Approved :: MIT License
Classifier: Natural Language :: English
Classifier: Operating System :: OS Independent
Classifier: Programming Language :: Python
Classifier: Programming Language :: Python :: 3
Classifier: Programming Language :: Python :: 3.8
Classifier: Programming Language :: Python :: 3.9
Classifier: Programming Language :: Python :: 3.10
Classifier: Programming Language :: Python :: 3.11
Classifier: Programming Language :: Python :: 3.12
Classifier: Programming Language :: Python :: 3.13
Classifier: Programming Language :: Python :: Implementation :: CPython
Classifier: Topic :: Scientific/Engineering :: Electronic Design Automation (EDA)
Classifier: Topic :: Software Development :: Libraries
Classifier: Topic :: Software Development :: Libraries :: Python Modules
Requires-Python: >=3.8
License-File: LICENSE
License-File: AUTHORS.md
Requires-Dist: pandas
Requires-Dist: openpyxl
Requires-Dist: simp_sexp
Provides-Extra: dev
Requires-Dist: pytest>=7.0; extra == "dev"
Requires-Dist: tox>=4.0.0; extra == "dev"
Dynamic: license-file
